.gitignore
MANIFEST.in
README.rst
apistar_pydantic.py
bitbucket-pipelines.yml
example.py
setup.cfg
setup.py
tests.py
tox.ini
.tox/py36/lib/python3.6/site-packages/Jinja2-2.10.dist-info/DESCRIPTION.rst
.tox/py36/lib/python3.6/site-packages/MarkupSafe-1.0.dist-info/DESCRIPTION.rst
.tox/py36/lib/python3.6/site-packages/Werkzeug-0.14.1.dist-info/DESCRIPTION.rst
.tox/py36/lib/python3.6/site-packages/apistar-0.3.9.dist-info/DESCRIPTION.rst
.tox/py36/lib/python3.6/site-packages/apistar_pydantic-0.0.1.dist-info/DESCRIPTION.rst
.tox/py36/lib/python3.6/site-packages/attrs-17.4.0.dist-info/DESCRIPTION.rst
.tox/py36/lib/python3.6/site-packages/certifi-2017.11.5.dist-info/DESCRIPTION.rst
.tox/py36/lib/python3.6/site-packages/chardet-3.0.4.dist-info/DESCRIPTION.rst
.tox/py36/lib/python3.6/site-packages/coreapi-2.3.3.dist-info/DESCRIPTION.rst
.tox/py36/lib/python3.6/site-packages/coreschema-0.0.4.dist-info/DESCRIPTION.rst
.tox/py36/lib/python3.6/site-packages/idna-2.6.dist-info/DESCRIPTION.rst
.tox/py36/lib/python3.6/site-packages/itypes-1.1.0.dist-info/DESCRIPTION.rst
.tox/py36/lib/python3.6/site-packages/pip-9.0.1.dist-info/DESCRIPTION.rst
.tox/py36/lib/python3.6/site-packages/pluggy-0.6.0.dist-info/DESCRIPTION.rst
.tox/py36/lib/python3.6/site-packages/py-1.5.2.dist-info/DESCRIPTION.rst
.tox/py36/lib/python3.6/site-packages/pydantic-0.6.3.dist-info/DESCRIPTION.rst
.tox/py36/lib/python3.6/site-packages/pytest-3.3.2.dist-info/DESCRIPTION.rst
.tox/py36/lib/python3.6/site-packages/requests-2.18.4.dist-info/DESCRIPTION.rst
.tox/py36/lib/python3.6/site-packages/setuptools-38.4.0.dist-info/DESCRIPTION.rst
.tox/py36/lib/python3.6/site-packages/six-1.11.0.dist-info/DESCRIPTION.rst
.tox/py36/lib/python3.6/site-packages/uritemplate-3.0.0.dist-info/DESCRIPTION.rst
.tox/py36/lib/python3.6/site-packages/urllib3-1.22.dist-info/DESCRIPTION.rst
.tox/py36/lib/python3.6/site-packages/wheel-0.30.0.dist-info/DESCRIPTION.rst
.tox/py36/lib/python3.6/site-packages/whitenoise-3.3.1.dist-info/DESCRIPTION.rst
.tox/py36/lib64/python3.6/site-packages/Jinja2-2.10.dist-info/DESCRIPTION.rst
.tox/py36/lib64/python3.6/site-packages/MarkupSafe-1.0.dist-info/DESCRIPTION.rst
.tox/py36/lib64/python3.6/site-packages/Werkzeug-0.14.1.dist-info/DESCRIPTION.rst
.tox/py36/lib64/python3.6/site-packages/apistar-0.3.9.dist-info/DESCRIPTION.rst
.tox/py36/lib64/python3.6/site-packages/apistar_pydantic-0.0.1.dist-info/DESCRIPTION.rst
.tox/py36/lib64/python3.6/site-packages/attrs-17.4.0.dist-info/DESCRIPTION.rst
.tox/py36/lib64/python3.6/site-packages/certifi-2017.11.5.dist-info/DESCRIPTION.rst
.tox/py36/lib64/python3.6/site-packages/chardet-3.0.4.dist-info/DESCRIPTION.rst
.tox/py36/lib64/python3.6/site-packages/coreapi-2.3.3.dist-info/DESCRIPTION.rst
.tox/py36/lib64/python3.6/site-packages/coreschema-0.0.4.dist-info/DESCRIPTION.rst
.tox/py36/lib64/python3.6/site-packages/idna-2.6.dist-info/DESCRIPTION.rst
.tox/py36/lib64/python3.6/site-packages/itypes-1.1.0.dist-info/DESCRIPTION.rst
.tox/py36/lib64/python3.6/site-packages/pip-9.0.1.dist-info/DESCRIPTION.rst
.tox/py36/lib64/python3.6/site-packages/pluggy-0.6.0.dist-info/DESCRIPTION.rst
.tox/py36/lib64/python3.6/site-packages/py-1.5.2.dist-info/DESCRIPTION.rst
.tox/py36/lib64/python3.6/site-packages/pydantic-0.6.3.dist-info/DESCRIPTION.rst
.tox/py36/lib64/python3.6/site-packages/pytest-3.3.2.dist-info/DESCRIPTION.rst
.tox/py36/lib64/python3.6/site-packages/requests-2.18.4.dist-info/DESCRIPTION.rst
.tox/py36/lib64/python3.6/site-packages/setuptools-38.4.0.dist-info/DESCRIPTION.rst
.tox/py36/lib64/python3.6/site-packages/six-1.11.0.dist-info/DESCRIPTION.rst
.tox/py36/lib64/python3.6/site-packages/uritemplate-3.0.0.dist-info/DESCRIPTION.rst
.tox/py36/lib64/python3.6/site-packages/urllib3-1.22.dist-info/DESCRIPTION.rst
.tox/py36/lib64/python3.6/site-packages/wheel-0.30.0.dist-info/DESCRIPTION.rst
.tox/py36/lib64/python3.6/site-packages/whitenoise-3.3.1.dist-info/DESCRIPTION.rst
.tox/pypy3/site-packages/pip-9.0.1.dist-info/DESCRIPTION.rst
.tox/pypy3/site-packages/py-1.4.34.dist-info/DESCRIPTION.rst
.tox/pypy3/site-packages/pytest-3.2.5.dist-info/DESCRIPTION.rst
.tox/pypy3/site-packages/setuptools-38.4.0.dist-info/DESCRIPTION.rst
.tox/pypy3/site-packages/wheel-0.30.0.dist-info/DESCRIPTION.rst
.venv/lib/python3.6/site-packages/Jinja2-2.10.dist-info/DESCRIPTION.rst
.venv/lib/python3.6/site-packages/PyYAML-3.12.dist-info/DESCRIPTION.rst
.venv/lib/python3.6/site-packages/Werkzeug-0.14.1.dist-info/DESCRIPTION.rst
.venv/lib/python3.6/site-packages/aiofiles-0.3.2.dist-info/DESCRIPTION.rst
.venv/lib/python3.6/site-packages/apistar-0.5.22.dist-info/DESCRIPTION.rst
.venv/lib/python3.6/site-packages/certifi-2018.4.16.dist-info/DESCRIPTION.rst
.venv/lib/python3.6/site-packages/chardet-3.0.4.dist-info/DESCRIPTION.rst
.venv/lib/python3.6/site-packages/click-6.7.dist-info/DESCRIPTION.rst
.venv/lib/python3.6/site-packages/idna-2.6.dist-info/DESCRIPTION.rst
.venv/lib/python3.6/site-packages/more_itertools-4.1.0.dist-info/DESCRIPTION.rst
.venv/lib/python3.6/site-packages/pip-9.0.3.dist-info/DESCRIPTION.rst
.venv/lib/python3.6/site-packages/pluggy-0.6.0.dist-info/DESCRIPTION.rst
.venv/lib/python3.6/site-packages/py-1.5.3.dist-info/DESCRIPTION.rst
.venv/lib/python3.6/site-packages/requests-2.18.4.dist-info/DESCRIPTION.rst
.venv/lib/python3.6/site-packages/setuptools-39.0.1.dist-info/DESCRIPTION.rst
.venv/lib/python3.6/site-packages/six-1.11.0.dist-info/DESCRIPTION.rst
.venv/lib/python3.6/site-packages/typed_ast-1.1.0.dist-info/DESCRIPTION.rst
.venv/lib/python3.6/site-packages/urllib3-1.22.dist-info/DESCRIPTION.rst
.venv/lib/python3.6/site-packages/whitenoise-3.3.1.dist-info/DESCRIPTION.rst
.venv/lib64/python3.6/site-packages/Jinja2-2.10.dist-info/DESCRIPTION.rst
.venv/lib64/python3.6/site-packages/PyYAML-3.12.dist-info/DESCRIPTION.rst
.venv/lib64/python3.6/site-packages/Werkzeug-0.14.1.dist-info/DESCRIPTION.rst
.venv/lib64/python3.6/site-packages/aiofiles-0.3.2.dist-info/DESCRIPTION.rst
