Metadata-Version: 1.1
Name: apistar-pydantic
Version: 0.0.5
Summary: Better handler parameters for APIStar (and pydantic support)
Home-page: https://github.com/pslacerda/apistar_pydantic
Author: Pedro Sousa Lacerda
Author-email: pslacerda@gmail.com
License: MIT license
Keywords: apistar_pydantic
Platform: UNKNOWN
Classifier: Development Status :: 2 - Pre-Alpha
Classifier: Intended Audience :: Developers
Classifier: License :: OSI Approved :: MIT License
Classifier: Natural Language :: English
Classifier: Programming Language :: Python :: 3
Classifier: Programming Language :: Python :: 3.6
